{
    "timestamp": "2026-02-03 05:51:58",
    "dataset": "BNP Paribas",
    "model": "ft_transformer",
    "seed": 52,
    "metrics": {
        "acc": 0.7836088515700166,
        "f1": 0.584831625528581,
        "auroc": 0.7556822223316535,
        "auprc": 0.9034416229980693,
        "inference_time_sec": 1.869877576828003,
        "throughput_samples_per_sec": 6114.304028071482
    },
    "config": {
        "model_name": "ft_transformer",
        "data_config_path": "configs/datasets/bnp.yaml",
        "dataset_name": "BNP Paribas",
        "gpu_ids": "0",
        "seed": "52",
        "optimize_metric": "acc",
        "n_numerical": "112",
        "n_categorical": "19",
        "n_features": "131",
        "total_cats": "16954",
        "task_type": "classification",
        "out_dim": "1",
        "batch_size": "512",
        "epochs": "100",
        "learning_rate": "3.082037213647568e-05",
        "weight_decay": "0.011833076335604277",
        "patience": "16",
        "n_layers": "2",
        "dropout": "0.1",
        "d_emb": "128",
        "d_token": "384",
        "d_ff_factor": "1.5932297010992813",
        "d_hidden_factor": "2.0",
        "n_heads": "8",
        "attention_dropout": "0.346674373051811",
        "ffn_dropout": "0.17527141729671336",
        "residual_dropout": "0.049345304569777",
        "n_experts": "4",
        "top_k": "2",
        "d_ff": "None",
        "router_noise_std": "0.1",
        "mu_init_strategy": "linspace",
        "lambda_spec": "0.1",
        "lambda_repel": "0.1",
        "lambda_bal": "0.001",
        "n_quantiles": "1000",
        "subsample": "100000",
        "use_raw_path": "True",
        "use_deep_path": "True",
        "use_dist_token": "True",
        "result_dir": "results/scores"
    }
}